dill_retnet/__init__.py
dill_retnet/dillretnet.py
dill_retnet-1.0.2.dist-info/licenses/LICENSE
dill_retnet-1.0.2.dist-info/METADATA
dill_retnet-1.0.2.dist-info/WHEEL
dill_retnet-1.0.2.dist-info/top_level.txt
dill_retnet-1.0.2.dist-info/RECORD
