Metadata-Version: 2.4
Name: dill-retnet
Version: 1.0.2
Summary: A simple but potentially powerful RetNet inspired model.
Home-page: https://github.com/dillfrescott/dill-retnet
Author: Cross Nastasi
Author-email: cross@dill.moe
Classifier: Programming Language :: Python :: 3
Classifier: License :: OSI Approved :: MIT License
Classifier: Operating System :: OS Independent
Requires-Python: >=3.6
License-File: LICENSE
Requires-Dist: torch
Dynamic: license-file
